susposter/__init__.py
susposter/susposter.c
susposter/susposter.png
susposter/sussy.png
susposter-1.17.7.dist-info/LICENSE
susposter-1.17.7.dist-info/WHEEL
susposter-1.17.7.dist-info/METADATA
susposter-1.17.7.dist-info/RECORD
