Metadata-Version: 2.1
Name: susposter
Version: 1.17.7
Summary: so sussy
Home-page: https://github.com/Cryptex-github
Author: Cryptex
Requires-Python: >=3.6,<4.0
Classifier: Programming Language :: Python :: 3
Classifier: Programming Language :: Python :: 3.6
Classifier: Programming Language :: Python :: 3.7
Classifier: Programming Language :: Python :: 3.8
Classifier: Programming Language :: Python :: 3.9
Project-URL: Repository, https://github.com/Cryptex-github
